main/qr_v2005.v
// Verilog-2005 compatible QR module
module QR (
    input  wire [31:0] in_a,
    input  wire [31:0] in_b,
    input  wire [31:0] in_c,
    input  wire [31:0] in_d,
    output reg  [31:0] out_a,
    output reg  [31:0] out_b,
    output reg  [31:0] out_c,
    output reg  [31:0] out_d
);

    // Declare variables outside the always block for Verilog-2005 compatibility
    reg [31:0] a, b, c, d;

    always @(*) begin
        // Initialize with input values for this round
        a = in_a;
        b = in_b;
        c = in_c;
        d = in_d;

        // --- Execute the ChaCha20 Quarter Round (RFC 8439) ---

        // Step 1
        a = a + b;
        d = d ^ a;
        d = (d << 16) | (d >> 16); // Rotate left by 16

        // Step 2
        c = c + d;
        b = b ^ c;
        b = (b << 12) | (b >> 20); // Rotate left by 12 (32-12=20)

        // Step 3
        a = a + b;
        d = d ^ a;
        d = (d << 8)  | (d >> 24); // Rotate left by 8 (32-8=24)

        // Step 4
        c = c + d;
        b = b ^ c;
        b = (b << 7)  | (b >> 25); // Rotate left by 7 (32-7=25)

        // Assign the final results to the output ports
        out_a = a;
        out_b = b;
        out_c = c;
        out_d = d;
    end

endmodule

main/rtl/chacha20_core/chacha20_core.v
module ChaCha20 (
    input wire clk,
    input wire rst_n, // Active-low reset input

    input wire start, // Start signal for the operation
    output wire busy, // Indicates core is processing
    output wire done, // Indicates operation is complete

    // Direct inputs for Key, Nonce, and Counter (TRNG acquisition removed)
    input wire [255:0] in_key,
    input wire [95:0]  in_nonce,
    input wire [31:0]  in_counter,

    input wire [511:0] in_state, // Main data input (plaintext for encrypt, ciphertext for decrypt)
    output wire [511:0] out_state, // Main data output (ciphertext for encrypt, plaintext for decrypt)

    // --- Temporary Debug Ports (for waveform visibility) ---
    output wire [511:0] debug_s,             // Current 's' state array
    output wire [511:0] debug_s_col_out,     // Output of column round (combinatorial)
    output wire [511:0] debug_s_round_result, // Output of diagonal round (combinatorial)
    output wire [3:0] debug_fsm_state,
    output wire [4:0] debug_round_count,
    output wire       debug_is_col_round
);

// Define the number of double-rounds (10 for ChaCha20)
localparam NUM_DOUBLE_ROUNDS = 10;

// ChaCha20 Internal State Register
reg [31:0] s [0:15]; // Array of 16 32-bit registers for the ChaCha20 state

// Debug Port Concatenations (connects internal arrays to 512-bit output wires)
assign debug_s = {s[15], s[14], s[13], s[12], s[11], s[10], s[9], s[8], s[7], s[6], s[5], s[4], s[3], s[2], s[1], s[0]};
assign debug_s_col_out = {s_col_out[15], s_col_out[14], s_col_out[13], s_col_out[12], s_col_out[11], s_col_out[10], s_col_out[9], s_col_out[8], s_col_out[7], s_col_out[6], s_col_out[5], s_col_out[4], s_col_out[3], s_col_out[2], s_col_out[1], s_col_out[0]};
assign debug_s_round_result = {s_round_result[15], s_round_result[14], s_round_result[13], s_round_result[12], s_round_result[11], s_round_result[10], s_round_result[9], s_round_result[8], s_round_result[7], s_round_result[6], s_round_result[5], s_round_result[4], s_round_result[3], s_round_result[2], s_round_result[1], s_round_result[0]};
assign debug_fsm_state = current_fsm_state;
assign debug_round_count = round_count;
assign debug_is_col_round = current_round_is_col;
// Defining the constants for the initial state
localparam C0 = 32'h61707865; // "expa"
localparam C1 = 32'h3320646e; // "nd 3"
localparam C2 = 32'h79622d32; // "2-by"
localparam C3 = 32'h6b206574; // "te k"

// Internal registers for FSM and data path
reg [511:0] original_state_copy; // Stores initial s state for final addition
reg [4:0] round_count;             // Tracks double-rounds (0 to NUM_DOUBLE_ROUNDS-1)
reg current_round_is_col; // 0: Diagonal round stage, 1: Column round stage
reg busy_reg;                      // Internal busy status register
reg done_reg;                      // Internal done status register
reg [511:0] out_state_reg;         // Internal register for out_state port
reg [511:0] full_keystream_block_temp; // Temporary storage for the 512-bit keystream

// Assign internal status registers to output ports
assign busy = busy_reg;
assign done = done_reg;
assign out_state = out_state_reg;


// --- Pipelined Round Logic (Combinatorial) ---
// These wires hold the combinatorial outputs of the QR instances
wire [31:0] s_col_out[0:15];      // Output of the column rounds (combinatorial)
wire [31:0] s_round_result[0:15]; // Output of the diagonal rounds (combinatorial)

// Register to pipeline the column round output into the diagonal round input
// This allows column round to happen in one cycle, diagonal in the next.
reg [31:0] s_col_reg[0:15]; 

// QR COLUMN rounds (operating on the current 's' state)
// s_col_out[i] represents the element at matrix position 'i' after column QR.
QR U_QR_COL_0 (.in_a(s[0]), .in_b(s[4]), .in_c(s[8]),  .in_d(s[12]), .out_a(s_col_out[0]),  .out_b(s_col_out[4]),  .out_c(s_col_out[8]),  .out_d(s_col_out[12]));
QR U_QR_COL_1 (.in_a(s[1]), .in_b(s[5]), .in_c(s[9]),  .in_d(s[13]), .out_a(s_col_out[1]),  .out_b(s_col_out[5]),  .out_c(s_col_out[9]),  .out_d(s_col_out[13]));
QR U_QR_COL_2 (.in_a(s[2]), .in_b(s[6]), .in_c(s[10]), .in_d(s[14]), .out_a(s_col_out[2]),  .out_b(s_col_out[6]),  .out_c(s_col_out[10]), .out_d(s_col_out[14]));
QR U_QR_COL_3 (.in_a(s[3]), .in_b(s[7]), .in_c(s[11]), .in_d(s[15]), .out_a(s_col_out[3]),  .out_b(s_col_out[7]),  .out_c(s_col_out[11]), .out_d(s_col_out[15]));

// QR DIAGONAL rounds (operating on the *registered* state after column rounds)
// s_round_result[i] represents the element at matrix position 'i' after diagonal QR.
QR U_QR_DIAG_0 (.in_a(s_col_reg[0]),  .in_b(s_col_reg[5]),  .in_c(s_col_reg[10]), .in_d(s_col_reg[15]), .out_a(s_round_result[0]),  .out_b(s_round_result[5]),  .out_c(s_round_result[10]), .out_d(s_round_result[15]));
QR U_QR_DIAG_1 (.in_a(s_col_reg[1]),  .in_b(s_col_reg[6]),  .in_c(s_col_reg[11]), .in_d(s_col_reg[12]), .out_a(s_round_result[1]),  .out_b(s_round_result[6]),  .out_c(s_round_result[11]), .out_d(s_round_result[12]));
QR U_QR_DIAG_2 (.in_a(s_col_reg[2]),  .in_b(s_col_reg[7]),  .in_c(s_col_reg[8]),  .in_d(s_col_reg[13]), .out_a(s_round_result[2]),  .out_b(s_round_result[7]),  .out_c(s_round_result[8]),  .out_d(s_round_result[13]));
QR U_QR_DIAG_3 (.in_a(s_col_reg[3]),  .in_b(s_col_reg[4]),  .in_c(s_col_reg[9]),  .in_d(s_col_reg[14]), .out_a(s_round_result[3]),  .out_b(s_round_result[4]),  .out_c(s_round_result[9]),  .out_d(s_round_result[14]));

// Finite State Machine (FSM) State Definitions
// These map to clock-cycle stages of the operation.
localparam  S_IDLE                 = 4'h0; // Core is waiting for a start signal
localparam  S_INIT_AND_COPY        = 4'h1; // Initialize 's' and 'original_state_copy' from inputs
localparam  S_RUN_ROUNDS           = 4'h2; // Perform Diagonal Round, latch results into 's' and increment round_count
localparam  S_GENERATE_OUTPUT      = 4'h3; // Generate keystream and final output
localparam  S_DONE_PULSE           = 4'h4; // Signal completion for one cycle

reg [3:0] current_fsm_state, next_fsm_state;

// FSM: Combinatorial Next State Logic
// Determines 'next_fsm_state' based on 'current_fsm_state' and inputs.
always @(*) begin
    next_fsm_state = current_fsm_state; // Default: stay in current state (unless transition condition met)

    case (current_fsm_state)
        S_IDLE : begin
            if (start) begin // If start signal is asserted, begin operation
                next_fsm_state = S_INIT_AND_COPY;
            end
        end
        S_INIT_AND_COPY : begin
        next_fsm_state = S_RUN_ROUNDS; // Move to the rounds super-state
        end
        S_RUN_ROUNDS : begin // This state runs for 20 cycles (10 double-rounds)
             if (round_count == (NUM_DOUBLE_ROUNDS - 1) && !current_round_is_col) begin
                next_fsm_state = S_GENERATE_OUTPUT;
            end else begin
                next_fsm_state = S_RUN_ROUNDS;
            end
        end
        // The logic for column/diagonal decision happens inside S_RUN_ROUNDS sequential block
        S_GENERATE_OUTPUT : begin // Final output calculation
            next_fsm_state = S_DONE_PULSE; // Move to signal completion
        end
        S_DONE_PULSE : begin // Signal completion for one cycle, then return to idle
            next_fsm_state = S_IDLE;
        end
        default: begin // Safety default for any undefined states
            next_fsm_state = S_IDLE;
        end
    endcase
end

// FSM: Sequential Logic
// Updates current_fsm_state and registers based on clock edge and reset.
always @(posedge clk or negedge rst_n) begin
    if (!rst_n) begin // Reset the whole machine and core to initial state
        current_fsm_state <= S_IDLE;
        busy_reg <= 1'b0;
        done_reg <= 1'b0;
        round_count <= 5'd0; // Reset round counter (0-9 for 10 double-rounds)
        current_round_is_col <= 1'b1;
        original_state_copy <= 512'b0; // Reset original state copy
        out_state_reg <= 512'b0; // Reset output register
        full_keystream_block_temp <= 512'b0; // Reset temporary keystream

        // Reset all internal state arrays
        for (int i = 0; i < 16; i = i + 1) begin
            s[i] <= 32'b0;
            s_col_reg[i] <= 32'b0; // Reset pipelining register
        end
    end else begin // Normal operation: on clock edge
        current_fsm_state <= next_fsm_state; // Update FSM state

        // Default busy/done assignments for active states (overridden below for IDLE/DONE)
        busy_reg <= 1'b1; // Default busy status for active states
        done_reg <= 1'b0; // Default not done by default
        out_state_reg <= 512'b0; // Default output to 0s to prevent X propagation
        full_keystream_block_temp <= 512'b0; // Default to 0s
        
        case (current_fsm_state) // Specific actions for each FSM state
            S_IDLE: begin
                busy_reg <= 1'b0; // Not busy when idle
                done_reg <= 1'b0; // Not done when idle
                round_count <= 5'd0; // Reset round count on starting new operation (or keep it in reset)
                current_round_is_col <= 1'b1;
            end
            S_INIT_AND_COPY: begin
                busy_reg <= 1'b1;
                
                // Load 's' registers
                s[0]  <= C0;
                s[1]  <= C1;
                s[2]  <= C2;
                s[3]  <= C3;
                s[4]  <= {in_key[231:224], in_key[239:232], in_key[247:240], in_key[255:248]}; // K0
                s[5]  <= {in_key[199:192], in_key[207:200], in_key[215:208], in_key[223:216]}; // K1
                s[6]  <= {in_key[167:160], in_key[175:168], in_key[183:176], in_key[191:184]}; // K2
                s[7]  <= {in_key[135:128], in_key[143:136], in_key[151:144], in_key[159:152]}; // K3
                s[8]  <= {in_key[103:96],  in_key[111:104], in_key[119:112], in_key[127:120]}; // K4
                s[9]  <= {in_key[71:64],   in_key[79:72],  in_key[87:80],  in_key[95:88]};   // K5
                s[10] <= {in_key[39:32],   in_key[47:40],  in_key[55:48],  in_key[63:56]};   // K6
                s[11] <= {in_key[7:0],     in_key[15:8],   in_key[23:16],  in_key[31:24]};   // K7
                s[12] <= {in_counter[7:0], in_counter[15:8], in_counter[23:16], in_counter[31:24]};
                s[13] <= {in_nonce[7:0],   in_nonce[15:8],   in_nonce[23:16],   in_nonce[31:24]};
                s[14] <= {in_nonce[39:32], in_nonce[47:40],  in_nonce[55:48],   in_nonce[63:56]};
                s[15] <= {in_nonce[71:64], in_nonce[79:72],  in_nonce[87:80],   in_nonce[95:88]};
                
                // Load 'original_state_copy' with the same values
                original_state_copy <= {
                    {in_nonce[71:64], in_nonce[79:72],  in_nonce[87:80],   in_nonce[95:88]},   // s[15]
                    {in_nonce[39:32], in_nonce[47:40],  in_nonce[55:48],   in_nonce[63:56]},   // s[14]
                    {in_nonce[7:0],   in_nonce[15:8],   in_nonce[23:16],   in_nonce[31:24]},   // s[13]
                    {in_counter[7:0], in_counter[15:8], in_counter[23:16], in_counter[31:24]}, // s[12]
                    {in_key[7:0],     in_key[15:8],   in_key[23:16],  in_key[31:24]},       // s[11]
                    {in_key[39:32],   in_key[47:40],  in_key[55:48],  in_key[63:56]},       // s[10]
                    {in_key[71:64],   in_key[79:72],  in_key[87:80],  in_key[95:88]},       // s[9]
                    {in_key[103:96],  in_key[111:104], in_key[119:112], in_key[127:120]},   // s[8]
                    {in_key[135:128], in_key[143:136], in_key[151:144], in_key[159:152]},   // s[7]
                    {in_key[167:160], in_key[175:168], in_key[183:176], in_key[191:184]},   // s[6]
                    {in_key[199:192], in_key[207:200], in_key[215:208], in_key[223:216]},   // s[5]
                    {in_key[231:224], in_key[239:232], in_key[247:240], in_key[255:248]},   // s[4]
                    C3, C2, C1, C0
                };
            end
            S_RUN_ROUNDS: begin
                if (current_round_is_col) begin // Execute Column Round actions
                    for (int i = 0; i < 16; i = i + 1) begin
                        s_col_reg[i] <= s_col_out[i];
                    end
                    current_round_is_col <= 1'b0; // Switch to Diagonal for next cycle
                end else begin // Execute Diagonal Round actions
                    for (int i = 0; i < 16; i++) begin
                        s[i] <= s_round_result[i];
                    end
                    round_count <= round_count + 1'b1; // Increment double-round counter
                    current_round_is_col <= 1'b1; // Switch back to Column for next double-round
                end
            end
            S_GENERATE_OUTPUT: begin
                // Calculate full keystream block (final s + original_state_copy)
                full_keystream_block_temp <= {
                    s[15] + original_state_copy[511:480],
                    s[14] + original_state_copy[479:448],
                    s[13] + original_state_copy[447:416],
                    s[12] + original_state_copy[415:384],
                    s[11] + original_state_copy[383:352],
                    s[10] + original_state_copy[351:320],
                    s[9]  + original_state_copy[319:288],
                    s[8]  + original_state_copy[287:256],
                    s[7]  + original_state_copy[255:224],
                    s[6]  + original_state_copy[223:192],
                    s[5]  + original_state_copy[191:160],
                    s[4]  + original_state_copy[159:128],
                    s[3]  + original_state_copy[127:96],
                    s[2]  + original_state_copy[95:64],
                    s[1]  + original_state_copy[63:32],
                    s[0]  + original_state_copy[31:0]
                }; 
            end
            S_DONE_PULSE : begin
                out_state_reg <= in_state ^ full_keystream_block_temp;
                busy_reg <= 1'b0; // Not busy anymore
                done_reg <= 1'b1; // Signal completion
            end
            default: begin
                // busy_reg, done_reg, out_state_reg, full_keystream_block_temp
                // are set by defaults at the start of the 'else' block.
            end
        endcase
    end
end

endmodule

main/tb/chacha20_core_tb.sv
`timescale 1ns / 1ps

// Final, Corrected Testbench for the ChaCha20 Core
module tb_ChaCha20;

    // Signal Declarations
    reg clk;
    reg rst_n;
    reg start;
    reg [255:0] in_key;
    reg [95:0]  in_nonce;
    reg [31:0]  in_counter;
    reg [511:0] in_state;
    reg [511:0] expected_out_state;

    wire busy;
    wire done;
    wire [511:0] out_state;

    // Wires for debug ports (optional but helpful)
    wire [511:0] debug_s;
    wire [511:0] debug_s_col_out;
    wire [511:0] debug_s_round_result;
    wire [3:0]   debug_fsm_state;
    wire [4:0]   debug_round_count;
    wire         debug_is_col_round;

    // DUT Instantiation using .* for convenience
    ChaCha20 UUT (.*);

    // Clock Generator
    always #5 clk = ~clk;

    // Main Test Sequence
    initial begin
        $display("STARTING ChaCha20 RFC 8439 TEST");
        $dumpfile("chacha20_rfc_tb.vcd");
        $dumpvars(0, tb_ChaCha20);

        // Initialize signals & load test vectors
        clk = 0;
        rst_n = 1;
        start = 0;
        in_state = 512'h0;

        // Use original Big-Endian literals for inputs, as the core now handles them correctly.
        in_key           = 256'h000102030405060708090a0b0c0d0e0f101112131415161718191a1b1c1d1e1f;
        in_nonce         =  96'h000000090000004a00000000;
        in_counter       =  32'h00000001;

        // --- THIS IS THE CORRECTED VALUE ---
        // This is the RFC byte stream, formatted as 16 little-endian 32-bit words,
        // then concatenated into a single 512-bit big-endian literal for Verilog.
        expected_out_state = 512'he4e7f11015593bd11fdd0f50c47120a336d6d0c72a083ed088090e429bcbe63bc5f2528343475fb479e94820f5e13100207f8fc891ca406348de53841cc5de62;

        // Reset the core
        rst_n = 0; #20; rst_n = 1; #10;

        // Start the operation
        start = 1; #10; start = 0;

        // Wait for completion
        wait (done);
        #10; // Allow final output to settle

        // Verify results
        $display("\n---------------------- FINAL STATE COMPARISON ----------------------");
        $display("DUT Output:      %h", out_state);
        $display("Expected Output: %h", expected_out_state);
        $display("--------------------------------------------------------------------\n");

        if (out_state === expected_out_state) begin
            $display("********************************************************************");
            $display("** SUCCESS: Core output perfectly matches RFC 8439 vector.        **");
            $display("********************************************************************");
        end else begin
            $display("!!!!!!!!!!!!!!!!!!!!!!!!!!!!!!!!!!!!!!!!!!!!!!!!!!!!!!!!!!!!!!!!!!!!");
            $display("!!   FAILURE: Core output DOES NOT match RFC 8439 vector.         !!");
            $display("!!!!!!!!!!!!!!!!!!!!!!!!!!!!!!!!!!!!!!!!!!!!!!!!!!!!!!!!!!!!!!!!!!!!");
        end

        $finish;
    end

endmodule

chacha20_rfc_tb.vcd
$date
	Wed Jul 23 02:13:41 2025
$end
$version
	Icarus Verilog
$end
$timescale
	1ps
$end
$scope module tb_ChaCha20 $end
$var wire 512 ! out_state [511:0] $end
$var wire 1 " done $end
$var wire 512 # debug_s_round_result [511:0] $end
$var wire 512 $ debug_s_col_out [511:0] $end
$var wire 512 % debug_s [511:0] $end
$var wire 5 & debug_round_count [4:0] $end
$var wire 1 ' debug_is_col_round $end
$var wire 4 ( debug_fsm_state [3:0] $end
$var wire 1 ) busy $end
$var reg 1 * clk $end
$var reg 512 + expected_out_state [511:0] $end
$var reg 32 , in_counter [31:0] $end
$var reg 256 - in_key [255:0] $end
$var reg 96 . in_nonce [95:0] $end
$var reg 512 / in_state [511:0] $end
$var reg 1 0 rst_n $end
$var reg 1 1 start $end
$scope module UUT $end
$var wire 1 ) busy $end
$var wire 1 * clk $end
$var wire 4 2 debug_fsm_state [3:0] $end
$var wire 1 ' debug_is_col_round $end
$var wire 5 3 debug_round_count [4:0] $end
$var wire 1 " done $end
$var wire 32 4 in_counter [31:0] $end
$var wire 256 5 in_key [255:0] $end
$var wire 96 6 in_nonce [95:0] $end
$var wire 512 7 in_state [511:0] $end
$var wire 512 8 out_state [511:0] $end
$var wire 1 0 rst_n $end
$var wire 1 1 start $end
$var wire 512 9 debug_s_round_result [511:0] $end
$var wire 512 : debug_s_col_out [511:0] $end
$var wire 512 ; debug_s [511:0] $end
$var parameter 32 < C0 $end
$var parameter 32 = C1 $end
$var parameter 32 > C2 $end
$var parameter 32 ? C3 $end
$var parameter 32 @ NUM_DOUBLE_ROUNDS $end
$var parameter 4 A S_DONE_PULSE $end
$var parameter 4 B S_GENERATE_OUTPUT $end
$var parameter 4 C S_IDLE $end
$var parameter 4 D S_INIT_AND_COPY $end
$var parameter 4 E S_RUN_ROUNDS $end
$var reg 1 F busy_reg $end
$var reg 4 G current_fsm_state [3:0] $end
$var reg 1 H current_round_is_col $end
$var reg 1 I done_reg $end
$var reg 512 J full_keystream_block_temp [511:0] $end
$var reg 4 K next_fsm_state [3:0] $end
$var reg 512 L original_state_copy [511:0] $end
$var reg 512 M out_state_reg [511:0] $end
$var reg 5 N round_count [4:0] $end
$scope module U_QR_COL_0 $end
$var wire 32 O in_a [31:0] $end
$var wire 32 P in_b [31:0] $end
$var wire 32 Q in_c [31:0] $end
$var wire 32 R in_d [31:0] $end
$var reg 32 S out_a [31:0] $end
$var reg 32 T out_b [31:0] $end
$var reg 32 U out_c [31:0] $end
$var reg 32 V out_d [31:0] $end
$scope begin $unm_blk_25 $end
$var reg 32 W a [31:0] $end
$var reg 32 X b [31:0] $end
$var reg 32 Y c [31:0] $end
$var reg 32 Z d [31:0] $end
$upscope $end
$upscope $end
$scope module U_QR_COL_1 $end
$var wire 32 [ in_a [31:0] $end
$var wire 32 \ in_b [31:0] $end
$var wire 32 ] in_c [31:0] $end
$var wire 32 ^ in_d [31:0] $end
$var reg 32 _ out_a [31:0] $end
$var reg 32 ` out_b [31:0] $end
$var reg 32 a out_c [31:0] $end
$var reg 32 b out_d [31:0] $end
$scope begin $unm_blk_25 $end
$var reg 32 c a [31:0] $end
$var reg 32 d b [31:0] $end
$var reg 32 e c [31:0] $end
$var reg 32 f d [31:0] $end
$upscope $end
$upscope $end
$scope module U_QR_COL_2 $end
$var wire 32 g in_a [31:0] $end
$var wire 32 h in_b [31:0] $end
$var wire 32 i in_c [31:0] $end
$var wire 32 j in_d [31:0] $end
$var reg 32 k out_a [31:0] $end
$var reg 32 l out_b [31:0] $end
$var reg 32 m out_c [31:0] $end
$var reg 32 n out_d [31:0] $end
$scope begin $unm_blk_25 $end
$var reg 32 o a [31:0] $end
$var reg 32 p b [31:0] $end
$var reg 32 q c [31:0] $end
$var reg 32 r d [31:0] $end
$upscope $end
$upscope $end
$scope module U_QR_COL_3 $end
$var wire 32 s in_a [31:0] $end
$var wire 32 t in_b [31:0] $end
$var wire 32 u in_c [31:0] $end
$var wire 32 v in_d [31:0] $end
$var reg 32 w out_a [31:0] $end
$var reg 32 x out_b [31:0] $end
$var reg 32 y out_c [31:0] $end
$var reg 32 z out_d [31:0] $end
$scope begin $unm_blk_25 $end
$var reg 32 { a [31:0] $end
$var reg 32 | b [31:0] $end
$var reg 32 } c [31:0] $end
$var reg 32 ~ d [31:0] $end
$upscope $end
$upscope $end
$scope module U_QR_DIAG_0 $end
$var wire 32 !" in_a [31:0] $end
$var wire 32 "" in_b [31:0] $end
$var wire 32 #" in_c [31:0] $end
$var wire 32 $" in_d [31:0] $end
$var reg 32 %" out_a [31:0] $end
$var reg 32 &" out_b [31:0] $end
$var reg 32 '" out_c [31:0] $end
$var reg 32 (" out_d [31:0] $end
$scope begin $unm_blk_25 $end
$var reg 32 )" a [31:0] $end
$var reg 32 *" b [31:0] $end
$var reg 32 +" c [31:0] $end
$var reg 32 ," d [31:0] $end
$upscope $end
$upscope $end
$scope module U_QR_DIAG_1 $end
$var wire 32 -" in_a [31:0] $end
$var wire 32 ." in_b [31:0] $end
$var wire 32 /" in_c [31:0] $end
$var wire 32 0" in_d [31:0] $end
$var reg 32 1" out_a [31:0] $end
$var reg 32 2" out_b [31:0] $end
$var reg 32 3" out_c [31:0] $end
$var reg 32 4" out_d [31:0] $end
$scope begin $unm_blk_25 $end
$var reg 32 5" a [31:0] $end
$var reg 32 6" b [31:0] $end
$var reg 32 7" c [31:0] $end
$var reg 32 8" d [31:0] $end
$upscope $end
$upscope $end
$scope module U_QR_DIAG_2 $end
$var wire 32 9" in_a [31:0] $end
$var wire 32 :" in_b [31:0] $end
$var wire 32 ;" in_c [31:0] $end
$var wire 32 <" in_d [31:0] $end
$var reg 32 =" out_a [31:0] $end
$var reg 32 >" out_b [31:0] $end
$var reg 32 ?" out_c [31:0] $end
$var reg 32 @" out_d [31:0] $end
$scope begin $unm_blk_25 $end
$var reg 32 A" a [31:0] $end
$var reg 32 B" b [31:0] $end
$var reg 32 C" c [31:0] $end
$var reg 32 D" d [31:0] $end
$upscope $end
$upscope $end
$scope module U_QR_DIAG_3 $end
$var wire 32 E" in_a [31:0] $end
$var wire 32 F" in_b [31:0] $end
$var wire 32 G" in_c [31:0] $end
$var wire 32 H" in_d [31:0] $end
$var reg 32 I" out_a [31:0] $end
$var reg 32 J" out_b [31:0] $end
$var reg 32 K" out_c [31:0] $end
$var reg 32 L" out_d [31:0] $end
$scope begin $unm_blk_25 $end
$var reg 32 M" a [31:0] $end
$var reg 32 N" b [31:0] $end
$var reg 32 O" c [31:0] $end
$var reg 32 P" d [31:0] $end
$upscope $end
$upscope $end
$scope begin $ivl_for_loop0 $end
$var integer 32 Q" i [31:0] $end
$upscope $end
$scope begin $ivl_for_loop1 $end
$var integer 32 R" i [31:0] $end
$upscope $end
$scope begin $ivl_for_loop2 $end
$var integer 32 S" i [31:0] $end
$upscope $end
$upscope $end
$upscope $end
$enddefinitions $end
$comment Show the parameter values. $end
$dumpall
b10 E
b1 D
b0 C
b11 B
b100 A
b1010 @
b1101011001000000110010101110100 ?
b1111001011000100010110100110010 >
b110011001000000110010001101110 =
b1100001011100000111100001100101 <
$end
#0
$dumpvars
b0 S"
b0 R"
b10000 Q"
b0 P"
b0 O"
b0 N"
b0 M"
b0 L"
b0 K"
b0 J"
b0 I"
b0 H"
b0 G"
b0 F"
b0 E"
b0 D"
b0 C"
b0 B"
b0 A"
b0 @"
b0 ?"
b0 >"
b0 ="
b0 <"
b0 ;"
b0 :"
b0 9"
b0 8"
b0 7"
b0 6"
b0 5"
b0 4"
b0 3"
b0 2"
b0 1"
b0 0"
b0 /"
b0 ."
b0 -"
b0 ,"
b0 +"
b0 *"
b0 )"
b0 ("
b0 '"
b0 &"
b0 %"
b0 $"
b0 #"
b0 ""
b0 !"
b0 ~
b0 }
b0 |
b0 {
b0 z
b0 y
b0 x
b0 w
b0 v
b0 u
b0 t
b0 s
b0 r
b0 q
b0 p
b0 o
b0 n
b0 m
b0 l
b0 k
b0 j
b0 i
b0 h
b0 g
b0 f
b0 e
b0 d
b0 c
b0 b
b0 a
b0 `
b0 _
b0 ^
b0 ]
b0 \
b0 [
b0 Z
b0 Y
b0 X
b0 W
b0 V
b0 U
b0 T
b0 S
b0 R
b0 Q
b0 P
b0 O
b0 N
b0 M
b0 L
b0 K
b0 J
0I
1H
b0 G
0F
b0 ;
b0 :
b0 9
b0 8
b0 7
b10010000000000000000000000000100101000000000000000000000000000000000 6
b1000000100000001100000100000001010000011000000111000010000000100100001010000010110000110000001101000011100000111100010000000100010001001000010011000101000001010100010110000101110001100000011001000110100001101100011100000111010001111000011111 5
b1 4
b0 3
b0 2
01
00
b0 /
b10010000000000000000000000000100101000000000000000000000000000000000 .
b1000000100000001100000100000001010000011000000111000010000000100100001010000010110000110000001101000011100000111100010000000100010001001000010011000101000001010100010110000101110001100000011001000110100001101100011100000111010001111000011111 -
b1 ,
b11100100111001111111000100010000000101010101100100111011110100010001111111011101000011110101000011000100011100010010000010100011001101101101011011010000110001110010101000001000001111101101000010001000000010010000111001000010100110111100101111100110001110111100010111110010010100101000001101000011010001110101111110110100011110011110100101001000001000001111010111100001001100010000000000100000011111111000111111001000100100011100101001000000011000110100100011011110010100111000010000011100110001011101111001100010 +
0*
0)
b0 (
1'
b0 &
b0 %
b0 $
b0 #
0"
b0 !
$end
#5000
b10000 Q"
1*
#10000
0*
#15000
b10000 Q"
1*
#20000
0*
10
#25000
0)
0F
1*
#30000
b1 K
0*
11
#35000
b10 K
0)
0F
b1 (
b1 2
b1 G
1*
#40000
b10 K
0*
01
#45000
b10000010101011110100011111110110 z
b10100010011011101100001000000 y
b11001100110110001101010010001110 x
b10000100000000101101110001101001 w
b10000010101011110100011111110110 ~
b10100010011011101100001000000 }
b11001100110110001101010010001110 |
b10000100000000101101110001101001 {
b1101110001101011011001101000101 n
b10111111100010101001101011001001 m
b10110001001011111011011000101000 l
b1110011010101001111101111011111 k
b1101110001101011011001101000101 r
b10111111100010101001101011001001 q
b10110001001011111011011000101000 p
b1110011010101001111101111011111 o
b10111000011010111100110001110111 b
b111000111101000001101110110001 a
b101011111110011110010011101110 `
b11110110010100101000111101010 _
b10111000011010111100110001110111 f
b111000111101000001101110110001 e
b101011111110011110010011101110 d
b11110110010100101000111101010 c
b10001111110001110010111011000010 V
b11100001111101010010101000100 U
b10100011010001101101100110100101 T
b10000010101011110100011111110110011011100011010110110011010001011011100001101011110011000111011110001111110001110010111011000010000101000100110111011000010000001011111110001010100110101100100100111000111101000001101110110001000111000011111010100101010001001100110011011000110101001000111010110001001011111011011000101000001010111111100111100100111011101010001101000110110110011010010110000100000000101101110001101001011100110101010011111011110111110001111011001010010100011110101010111011111010101010001001011100 $
b10000010101011110100011111110110011011100011010110110011010001011011100001101011110011000111011110001111110001110010111011000010000101000100110111011000010000001011111110001010100110101100100100111000111101000001101110110001000111000011111010100101010001001100110011011000110101001000111010110001001011111011011000101000001010111111100111100100111011101010001101000110110110011010010110000100000000101101110001101001011100110101010011111011110111110001111011001010010100011110101010111011111010101010001001011100 :
b10111011111010101010001001011100 S
b10001111110001110010111011000010 Z
b11100001111101010010101000100 Y
b10100011010001101101100110100101 X
b10111011111010101010001001011100 W
b1001000000000000000000000000010010100000000000000000000000000000000000000000000000000000000000000001000000000000000000000000000111110001111000011101000111000001101100011010000110010001100000010111000101100001010100010100000100110001001000010001000100000000111100001110000011010000110000001011000010100000100100001000000001110000011000000101000001000000001100000010000000010000000001101011001000000110010101110100011110010110001000101101001100100011001100100000011001000110111001100001011100000111100001100101 L
b1001000000000000000000000000 v
b1001010000000000000000000000000 j
b1000000000000000000000000 R
b11111000111100001110100011100 u
b11011000110100001100100011000 i
b10111000101100001010100010100 ]
b10011000100100001000100010000 Q
b1111000011100000110100001100 t
b1011000010100000100100001000 h
b111000001100000010100000100 \
b11000000100000000100000000 P
b1101011001000000110010101110100 s
b1111001011000100010110100110010 g
b110011001000000110010001101110 [
b1001000000000000000000000000010010100000000000000000000000000000000000000000000000000000000000000001000000000000000000000000000111110001111000011101000111000001101100011010000110010001100000010111000101100001010100010100000100110001001000010001000100000000111100001110000011010000110000001011000010100000100100001000000001110000011000000101000001000000001100000010000000010000000001101011001000000110010101110100011110010110001000101101001100100011001100100000011001000110111001100001011100000111100001100101 %
b1001000000000000000000000000010010100000000000000000000000000000000000000000000000000000000000000001000000000000000000000000000111110001111000011101000111000001101100011010000110010001100000010111000101100001010100010100000100110001001000010001000100000000111100001110000011010000110000001011000010100000100100001000000001110000011000000101000001000000001100000010000000010000000001101011001000000110010101110100011110010110001000101101001100100011001100100000011001000110111001100001011100000111100001100101 ;
b1100001011100000111100001100101 O
1)
1F
b10 (
b10 2
b10 G
1*
#50000
0*
