main/asic_top_simple.v
// Simplified asic_top for testing basic functionality
module asic_top (
    input wire clk,
    input wire rst_n,
    input wire start,
    output reg busy,
    output reg done,

    // Streaming state input (plaintext) - 32 bits wide
    input wire [31:0] in_state_word,
    input wire in_state_valid,
    output reg in_state_ready,

    // Streaming state output (ciphertext) - 32 bits wide
    output reg [31:0] out_state_word,
    output reg out_state_valid,
    input wire out_state_ready,

    input wire use_streamed_key,
    input wire use_streamed_nonce,
    input wire use_streamed_counter,

    input wire [1:0] chunk_type,
    input wire chunk_valid,
    input wire [31:0] chunk,
    output reg [4:0] chunk_index,
    output reg chunk_request,
    output reg [1:0] request_type,

    // TRNG signals
    input wire [31:0] trng_data,
    input wire trng_ready,
    output reg trng_request
);

    // Simple FSM states
    reg [2:0] state;
    parameter IDLE = 3'b000;
    parameter REQ_TRNG = 3'b001;
    parameter WAIT_TRNG = 3'b010;
    parameter PROCESSING = 3'b011;
    parameter COMPLETE = 3'b100;

    reg [3:0] counter;

    always @(posedge clk or negedge rst_n) begin
        if (!rst_n) begin
            state <= IDLE;
            busy <= 0;
            done <= 0;
            trng_request <= 0;
            chunk_request <= 0;
            request_type <= 0;
            chunk_index <= 0;
            counter <= 0;
            in_state_ready <= 0;
            out_state_valid <= 0;
            out_state_word <= 0;
        end else begin
            // Default values
            trng_request <= 0;
            chunk_request <= 0;
            done <= 0;
            in_state_ready <= 0;
            out_state_valid <= 0;

            case (state)
                IDLE: begin
                    busy <= 0;
                    if (start) begin
                        busy <= 1;
                        state <= REQ_TRNG;
                        counter <= 0;
                    end
                end

                REQ_TRNG: begin
                    trng_request <= 1;
                    if (trng_ready) begin
                        state <= WAIT_TRNG;
                    end
                end

                WAIT_TRNG: begin
                    // Simple processing - just copy TRNG data to output
                    out_state_word <= trng_data;
                    out_state_valid <= 1;
                    if (out_state_ready) begin
                        counter <= counter + 1;
                        if (counter >= 15) begin // Output 16 words
                            state <= COMPLETE;
                        end else begin
                            state <= REQ_TRNG; // Get more data
                        end
                    end
                end

                COMPLETE: begin
                    done <= 1;
                    busy <= 0;
                    state <= IDLE;
                end

                default: state <= IDLE;
            endcase
        end
    end

endmodule

main/rtl/MockTRNGHardened.v
// Mock TRNGHardened module for simulation purposes
module MockTRNGHardened (
    input wire clk,
    input wire rst_n, // Active-low reset
    input wire trng_request, // Request from ASIC
    output reg [31:0] random_number,
    output reg ready // TRNG asserts when random_number is valid
);

    reg [31:0] internal_counter;

    always @(posedge clk or negedge rst_n) begin
        if (!rst_n) begin
            internal_counter <= 0;
            random_number <= 0;
            ready <= 0;
        end else begin
            ready <= 0; // Default to not ready
            if (trng_request) begin
                // In a real TRNG, this would take time to generate entropy.
                // For mock, we make it ready in the next cycle.
                internal_counter <= internal_counter + 1; // Generate next 'random' number
                random_number <= internal_counter + 1; // Output the next number
                ready <= 1; // Signal readiness
            end
        end
    end
endmodule

main/basic_test.v
`timescale 1ns / 1ps

// Basic functionality test without SystemVerilog features
module basic_asic_test;

    reg clk, rst_n, start;
    wire busy, done;
    
    // Test signals
    reg [31:0] in_state_word;
    reg in_state_valid;
    wire in_state_ready;
    wire [31:0] out_state_word;
    wire out_state_valid;
    reg out_state_ready;
    
    reg use_streamed_key, use_streamed_nonce, use_streamed_counter;
    reg [1:0] chunk_type;
    reg chunk_valid;
    reg [31:0] chunk;
    wire [4:0] chunk_index;
    wire chunk_request;
    wire [1:0] request_type;
    
    wire [31:0] trng_data;
    wire trng_ready;
    wire trng_request;

    // Instantiate the mock TRNG
    MockTRNGHardened mock_trng (
        .clk(clk),
        .rst_n(rst_n),
        .trng_request(trng_request),
        .random_number(trng_data),
        .ready(trng_ready)
    );

    // Instantiate the DUT
    asic_top dut (
        .clk(clk),
        .rst_n(rst_n),
        .start(start),
        .busy(busy),
        .done(done),
        .in_state_word(in_state_word),
        .in_state_valid(in_state_valid),
        .in_state_ready(in_state_ready),
        .out_state_word(out_state_word),
        .out_state_valid(out_state_valid),
        .out_state_ready(out_state_ready),
        .use_streamed_key(use_streamed_key),
        .use_streamed_nonce(use_streamed_nonce),
        .use_streamed_counter(use_streamed_counter),
        .chunk_type(chunk_type),
        .chunk_valid(chunk_valid),
        .chunk(chunk),
        .chunk_index(chunk_index),
        .chunk_request(chunk_request),
        .request_type(request_type),
        .trng_data(trng_data),
        .trng_ready(trng_ready),
        .trng_request(trng_request)
    );

    // Clock generation
    always #5 clk = ~clk;

    // Test sequence
    initial begin
        $dumpfile("basic_test.vcd");
        $dumpvars(0, basic_asic_test);
        
        // Initialize signals
        clk = 0;
        rst_n = 0;
        start = 0;
        use_streamed_key = 0;
        use_streamed_nonce = 0;
        use_streamed_counter = 0;
        chunk_type = 0;
        chunk_valid = 0;
        chunk = 0;
        in_state_word = 0;
        in_state_valid = 0;
        out_state_ready = 1;
        
        $display("=== Basic ASIC Test Started ===");
        
        // Reset sequence
        #20 rst_n = 1;
        #10;
        
        $display("Reset complete. Design state - Busy: %b, Done: %b", busy, done);
        
        // Test 1: Just check if design responds to start
        $display("Test 1: Checking start response...");
        start = 1;
        #10 start = 0;
        
        // Wait a bit and check status
        #50;
        $display("After start - Busy: %b, Done: %b, Chunk_req: %b, TRNG_req: %b", 
                 busy, done, chunk_request, trng_request);
        
        // If TRNG is requested, we know the design is using TRNG mode
        if (trng_request) begin
            $display("Design is requesting TRNG data - providing mock data");
            // The MockTRNG should handle this automatically
        end
        
        // If chunk is requested, we know the design wants streamed input
        if (chunk_request) begin
            $display("Design is requesting chunk data - Type: %b, Index: %d", 
                     request_type, chunk_index);
        end
        
        // Wait longer to see what happens
        #1000;
        
        $display("Final state - Busy: %b, Done: %b", busy, done);
        
        if (done) begin
            $display("✅ Design completed successfully!");
        end else if (busy) begin
            $display("⚠️  Design is still busy - may need more input or time");
        end else begin
            $display("❓ Design is idle - check if it started properly");
        end
        
        $display("=== Test Complete ===");
        $finish;
    end

    // Safety timeout
    initial begin
        #10000;
        $display("TIMEOUT: Test exceeded maximum time");
        $finish;
    end

endmodule

main/basic_test.vcd
$date
	Tue Jul 29 13:51:34 2025
$end
$version
	Icarus Verilog
$end
$timescale
	1ps
$end
$scope module basic_asic_test $end
$var wire 1 ! busy $end
$var wire 5 " chunk_index [4:0] $end
$var wire 1 # chunk_request $end
$var wire 1 $ done $end
$var wire 1 % in_state_ready $end
$var wire 1 & out_state_valid $end
$var wire 32 ' out_state_word [31:0] $end
$var wire 2 ( request_type [1:0] $end
$var wire 32 ) trng_data [31:0] $end
$var wire 1 * trng_ready $end
$var wire 1 + trng_request $end
$var reg 32 , chunk [31:0] $end
$var reg 2 - chunk_type [1:0] $end
$var reg 1 . chunk_valid $end
$var reg 1 / clk $end
$var reg 1 0 in_state_valid $end
$var reg 32 1 in_state_word [31:0] $end
$var reg 1 2 out_state_ready $end
$var reg 1 3 rst_n $end
$var reg 1 4 start $end
$var reg 1 5 use_streamed_counter $end
$var reg 1 6 use_streamed_key $end
$var reg 1 7 use_streamed_nonce $end
$scope module mock_trng $end
$var wire 1 8 clk $end
$var wire 1 9 rst_n $end
$var wire 1 + trng_request $end
$var reg 32 : internal_counter [31:0] $end
$var reg 32 ; random_number [31:0] $end
$var reg 1 < ready $end
$upscope $end
$scope module dut $end
$var wire 32 = chunk [31:0] $end
$var wire 2 > chunk_type [1:0] $end
$var wire 1 ? chunk_valid $end
$var wire 1 8 clk $end
$var wire 1 @ in_state_valid $end
$var wire 32 A in_state_word [31:0] $end
$var wire 1 B out_state_ready $end
$var wire 1 9 rst_n $end
$var wire 1 C start $end
$var wire 32 D trng_data [31:0] $end
$var wire 1 * trng_ready $end
$var wire 1 E use_streamed_counter $end
$var wire 1 F use_streamed_key $end
$var wire 1 G use_streamed_nonce $end
$var reg 1 H busy $end
$var reg 5 I chunk_index [4:0] $end
$var reg 1 J chunk_request $end
$var reg 4 K counter [3:0] $end
$var reg 1 L done $end
$var reg 1 M in_state_ready $end
$var reg 1 N out_state_valid $end
$var reg 32 O out_state_word [31:0] $end
$var reg 2 P request_type [1:0] $end
$var reg 3 Q state [2:0] $end
$var reg 1 R trng_request $end
$upscope $end
$upscope $end
$enddefinitions $end
#0
$dumpvars
0R
b0 Q
b0 P
b0 O
0N
0M
0L
b0 K
0J
b0 I
0H
0G
0F
0E
b0 D
0C
1B
b0 A
0@
0?
b0 >
b0 =
0<
b0 ;
b0 :
09
08
07
06
05
04
03
12
b0 1
00
0/
0.
b0 -
b0 ,
0+
0*
b0 )
b0 (
b0 '
0&
0%
0$
0#
b0 "
0!
$end
#5000
1/
18
#10000
0/
08
#15000
1/
18
#20000
0/
08
13
19
#25000
1/
18
#30000
0/
08
14
1C
#35000
b1 Q
1H
1!
1/
18
#40000
0/
08
04
0C
#45000
1R
1+
1/
18
#50000
0/
08
#55000
1<
1*
b1 ;
b1 )
b1 D
b1 :
1R
1+
1/
18
#60000
0/
08
#65000
b10 Q
1R
1+
b10 ;
b10 )
b10 D
b10 :
1<
1*
1/
18
#70000
0/
08
#75000
b11 ;
b11 )
b11 D
b11 :
1<
1*
b1 Q
b1 K
1N
1&
b10 O
b10 '
0R
0+
1/
18
#80000
0/
08
#85000
b10 Q
1R
1+
0N
0&
0<
0*
1/
18
#90000
0/
08
#95000
1<
1*
b100 ;
b100 )
b100 D
b100 :
b1 Q
b10 K
1N
1&
b11 O
b11 '
0R
0+
1/
18
#100000
0/
08
#105000
b10 Q
1R
1+
0N
0&
0<
0*
1/
18
#110000
0/
08
#115000
1<
1*
b101 ;
b101 )
b101 D
b101 :
b1 Q
b11 K
1N
1&
b100 O
b100 '
0R
0+
1/
18
#120000
0/
08
#125000
b10 Q
1R
1+
0N
0&
0<
0*
1/
18
#130000
0/
08
#135000
1<
1*
b110 ;
b110 )
b110 D
b110 :
b1 Q
b100 K
1N
1&
b101 O
b101 '
0R
0+
1/
18
#140000
0/
08
#145000
b10 Q
1R
1+
0N
0&
0<
0*
1/
18
#150000
0/
08
#155000
1<
1*
b111 ;
b111 )
b111 D
b111 :
b1 Q
b101 K
1N
1&
b110 O
b110 '
0R
0+
1/
18
#160000
0/
08
#165000
b10 Q
1R
1+
0N
0&
0<
0*
1/
18
#170000
0/
08
#175000
1<
1*
b1000 ;
b1000 )
b1000 D
b1000 :
b1 Q
b110 K
1N
1&
b111 O
b111 '
0R
0+
1/
18
#180000
0/
08
#185000
b10 Q
1R
1+
0N
0&
0<
0*
1/
18
#190000
0/
08
#195000
1<
1*
b1001 ;
b1001 )
b1001 D
b1001 :
b1 Q
b111 K
1N
1&
b1000 O
b1000 '
0R
0+
1/
18
#200000
0/
08
#205000
b10 Q
1R
1+
0N
0&
0<
0*
1/
18
#210000
0/
08
#215000
1<
1*
b1010 ;
b1010 )
b1010 D
b1010 :
b1 Q
b1000 K
1N
1&
b1001 O
b1001 '
0R
0+
1/
18
#220000
0/
08
#225000
b10 Q
1R
1+
0N
0&
0<
0*
1/
18
#230000
0/
08
#235000
1<
1*
b1011 ;
b1011 )
b1011 D
b1011 :
b1 Q
b1001 K
1N
1&
b1010 O
b1010 '
0R
0+
1/
18
#240000
0/
08
#245000
b10 Q
1R
1+
0N
0&
0<
0*
1/
18
#250000
0/
08
#255000
1<
1*
b1100 ;
b1100 )
b1100 D
b1100 :
b1 Q
b1010 K
1N
1&
b1011 O
b1011 '
0R
0+
1/
18
#260000
0/
08
#265000
b10 Q
1R
1+
0N
0&
0<
0*
1/
18
#270000
0/
08
#275000
1<
1*
b1101 ;
b1101 )
b1101 D
b1101 :
b1 Q
b1011 K
1N
1&
b1100 O
b1100 '
0R
0+
1/
18
#280000
0/
08
#285000
b10 Q
1R
1+
0N
0&
0<
0*
1/
18
#290000
0/
08
#295000
1<
1*
b1110 ;
b1110 )
b1110 D
b1110 :
b1 Q
b1100 K
1N
1&
b1101 O
b1101 '
0R
0+
1/
18
#300000
0/
08
#305000
b10 Q
1R
1+
0N
0&
0<
0*
1/
18
#310000
0/
08
#315000
1<
1*
b1111 ;
b1111 )
b1111 D
b1111 :
b1 Q
b1101 K
1N
1&
b1110 O
b1110 '
0R
0+
1/
18
#320000
0/
08
#325000
b10 Q
1R
1+
0N
0&
0<
0*
1/
18
#330000
0/
08
#335000
1<
1*
b10000 ;
b10000 )
b10000 D
b10000 :
b1 Q
b1110 K
1N
1&
b1111 O
b1111 '
0R
0+
1/
18
#340000
0/
08
#345000
b10 Q
1R
1+
0N
0&
0<
0*
1/
18
#350000
0/
08
#355000
1<
1*
b10001 ;
b10001 )
b10001 D
b10001 :
b1 Q
b1111 K
1N
1&
b10000 O
b10000 '
0R
0+
1/
18
#360000
0/
08
#365000
b10 Q
1R
1+
0N
0&
0<
0*
1/
18
#370000
0/
08
#375000
1<
1*
b10010 ;
b10010 )
b10010 D
b10010 :
b100 Q
b0 K
1N
1&
b10001 O
b10001 '
0R
0+
1/
18
#380000
0/
08
#385000
b0 Q
0H
0!
1L
1$
0N
0&
0<
0*
1/
18
#390000
0/
08
#395000
0L
0$
1/
18
